fstrm/__init__.py
fstrm/fstrm_codec.py
fstrm-0.6.1.dist-info/LICENSE
fstrm-0.6.1.dist-info/METADATA
fstrm-0.6.1.dist-info/WHEEL
fstrm-0.6.1.dist-info/top_level.txt
fstrm-0.6.1.dist-info/RECORD
