Metadata-Version: 2.1
Name: fstrm
Version: 0.6.1
Summary: Frame Streams implementation in Python
Home-page: https://github.com/dmachard/python-framestream
Author: Denis MACHARD
Author-email: d.machard@gmail.com
Keywords: framestreams fstrm encoder decoder
Platform: any
Classifier: License :: OSI Approved :: MIT License
Classifier: Programming Language :: Python :: 3
Classifier: Operating System :: OS Independent
Classifier: Topic :: Software Development :: Libraries
License-File: LICENSE
